uuid_backport/__init__.py
uuid_backport/_backport.py
uuid_backport-0.1.1.dist-info/WHEEL
uuid_backport-0.1.1.dist-info/METADATA
uuid_backport-0.1.1.dist-info/RECORD
