Metadata-Version: 2.3
Name: uuid-backport
Version: 0.1.1
Summary: Backport of Python 3.14 UUID module (RFC 9562) for Python 3.9+
Keywords: uuid,uuid6,uuid7,uuid8,rfc9562,backport
Author: Minsoo Jun
License: MIT License
Classifier: Development Status :: 4 - Beta
Classifier: Intended Audience :: Developers
Classifier: License :: OSI Approved :: MIT License
Classifier: Operating System :: OS Independent
Classifier: Programming Language :: Python :: 3
Classifier: Programming Language :: Python :: 3.9
Classifier: Programming Language :: Python :: 3.10
Classifier: Programming Language :: Python :: 3.11
Classifier: Programming Language :: Python :: 3.12
Classifier: Programming Language :: Python :: 3.13
Classifier: Topic :: Software Development :: Libraries :: Python Modules
Classifier: Topic :: Utilities
Requires-Python: >=3.9
Project-URL: Homepage, https://github.com/line1029/uuid-backport
Project-URL: Issues, https://github.com/line1029/uuid-backport/issues
Project-URL: Repository, https://github.com/line1029/uuid-backport
